{"adm_cd":"11100520","name":"서울특별시 도봉구 쌍문2동","rank":35,"rank_sido":26,"sido":"서울특별시","sgg":"도봉구","score":0.6969,"town_tag":"","center":{"lat":37.65536355442083,"lon":127.03641877915844},"boundary":{"id":"144","type":"Feature","properties":{"adm_nm":"서울특별시 도봉구 쌍문2동","adm_cd2":"1132067000","sgg":"11320","sido":"11","sidonm":"서울특별시","sggnm":"도봉구","adm_cd":"11100520"},"geometry":{"type":"Polygon","coordinates":[[[127.04222166699424,37.66170859913057],[127.04172969388993,37.660369493057935],[127.03633142639501,37.65137319077052],[127.03329480878855,37.65114377439794],[127.03294687801241,37.65261044348204],[127.0330501964656,37.653195593965975],[127.03383857684038,37.65402456160561],[127.03438231896774,37.656702547236044],[127.03417740256562,37.65952549407307],[127.03378509816372,37.66008244714331],[127.03491037176373,37.66032464422998],[127.03775427618218,37.66175088941333],[127.04222166699424,37.66170859913057]]]}},"station":{"name":"쌍문","lat":37.6484028,"lon":127.0345788,"dist_m":1002,"n_clinic_500m":13},"metrics":{"c_norm":0.5383,"p_norm":0.9785,"t_norm":0.1434,"pop_total":17315,"pop_40plus":11553,"ratio_40plus":0.6672,"catchment_pop_1_5km":188852,"catchment_pop_40plus":126002,"density_per_10k":0.238,"t_raw":40,"t_transit":47,"n_clinic":8,"n_clinic_med":3,"n_doctors_med":3,"n_clinic_gi":0,"n_clinic_500m":11,"n_clinic_1km":40,"n_clinic_2km":104,"n_within_radius_med":22,"n_within_radius_all":73,"n_doctors_within_radius_med":26,"med_desert":false,"centroid_mismatch":false,"suburban":false},"survey_links":{"kakao_map":"https://map.kakao.com/?q=서울특별시+도봉구+쌍문2동","naver_map":"https://map.naver.com/v5/search/서울특별시+도봉구+쌍문2동","naver_estate":"https://land.naver.com/sales?ms=37.65536355442083,127.03641877915844,16&filter=PWR&a=SG&b=A1&e=RETAIL"},"clinics":[{"name":"가톨릭성모의원","lat":37.6546524,"lon":127.0378725,"dist":150,"kind":"의원","is_gi":false,"drs":1,"addr":"서울특별시 도봉구 도봉로 553, (쌍문동)","tel":"02-903-4340","estb_year":"1992"},{"name":"김윤자내과의원","lat":37.6546524,"lon":127.0378725,"dist":150,"kind":"의원","is_gi":false,"drs":1,"addr":"서울특별시 도봉구 도봉로 553, 2층 (쌍문동, 상수빌딩)","tel":"6959-5220","estb_year":"2014"},{"name":"비-스킨피부과의원","lat":37.6564112,"lon":127.038806,"dist":240,"kind":"의원","is_gi":false,"drs":1,"addr":"서울특별시 도봉구 도봉로 575, 307호 (쌍문동, 삼환프라자)","tel":"02-903-9770","estb_year":"2002"},{"name":"위플러스내과의원","lat":37.6564112,"lon":127.038806,"dist":240,"kind":"의원","is_gi":false,"drs":1,"addr":"서울특별시 도봉구 도봉로 575, 삼환프라자 401, 402호 (쌍문동)","tel":"02-995-1119","estb_year":"2022"},{"name":"한얼통증의학과의원","lat":37.6564112,"lon":127.038806,"dist":240,"kind":"의원","is_gi":false,"drs":1,"addr":"서울특별시 도봉구 도봉로 575, 3층 306호 (쌍문동, 삼환프라자)","tel":"02-900-8872","estb_year":"2002"},{"name":"최병국내과의원","lat":37.6582071,"lon":127.035725,"dist":321,"kind":"의원","is_gi":false,"drs":1,"addr":"서울특별시 도봉구 해등로 190, 207호 (쌍문동, 신원상가)","tel":"02-902-6991","estb_year":"1999"},{"name":"하늘숲소아청소년과의원","lat":37.6584222,"lon":127.0353016,"dist":353,"kind":"의원","is_gi":false,"drs":1,"addr":"서울특별시 도봉구 도당로 2, 4층 (쌍문동)","tel":"02-904-3553","estb_year":"2015"},{"name":"정다운가정의학과의원","lat":37.6556381,"lon":127.0414985,"dist":449,"kind":"의원","is_gi":false,"drs":1,"addr":"서울특별시 도봉구 해등로16길 26, (창동, 타임프라자)","tel":"997-7545","estb_year":"2016"},{"name":"가족건강의원","lat":37.6581634,"lon":127.0325391,"dist":462,"kind":"의원","is_gi":false,"drs":1,"addr":"서울특별시 도봉구 해등로 218, (쌍문동)","tel":"02-903-1556","estb_year":"1989"},{"name":"쌍문동강내과의원","lat":37.6581634,"lon":127.0325391,"dist":462,"kind":"의원","is_gi":false,"drs":1,"addr":"서울특별시 도봉구 해등로 218, (쌍문동)","tel":"02-998-3600","estb_year":"2013"},{"name":"정진영정형외과의원","lat":37.6583821,"lon":127.0400625,"dist":464,"kind":"의원","is_gi":false,"drs":1,"addr":"서울특별시 도봉구 도봉로 601, 2층 (쌍문동, 시그마빌딩)","tel":"02-990-9225","estb_year":"1997"},{"name":"쌍문성모내과의원","lat":37.6510978,"lon":127.0357293,"dist":477,"kind":"의원","is_gi":false,"drs":2,"addr":"서울특별시 도봉구 도봉로 511, 2~4층 (쌍문동)","tel":"02-903-0875","estb_year":"2001"},{"name":"건강제일의원","lat":37.6501944,"lon":127.0353357,"dist":581,"kind":"의원","is_gi":false,"drs":1,"addr":"서울특별시 도봉구 도봉로 499, 2호 (쌍문동)","tel":"02-903-0099","estb_year":"2007"},{"name":"서울내과의원","lat":37.6489936,"lon":127.0352813,"dist":713,"kind":"의원","is_gi":false,"drs":2,"addr":"서울특별시 도봉구 도봉로 488, (창동)","tel":"02-905-6119","estb_year":"1999"},{"name":"서울항맥외과의원","lat":37.6489936,"lon":127.0352813,"dist":713,"kind":"의원","is_gi":false,"drs":1,"addr":"서울특별시 도봉구 도봉로 488, 6층 (창동, 대명빌딩)","tel":"02-997-0700","estb_year":"2010"},{"name":"이수현내과의원","lat":37.6574763,"lon":127.0284807,"dist":738,"kind":"의원","is_gi":false,"drs":1,"addr":"서울특별시 도봉구 해등로 255, (쌍문동)","tel":"02-903-0092","estb_year":"1994"},{"name":"클로바의원","lat":37.6486177,"lon":127.0350858,"dist":757,"kind":"의원","is_gi":false,"drs":1,"addr":"서울특별시 도봉구 도봉로 484, (창동)","tel":"02-904-8500","estb_year":"2001"},{"name":"향림마취과의원","lat":37.6486177,"lon":127.0350858,"dist":757,"kind":"의원","is_gi":false,"drs":1,"addr":"서울특별시 도봉구 도봉로 484, 301호 (창동, 청우빌딩)","tel":"02-999-0506","estb_year":"1998"},{"name":"한국정형외과의원","lat":37.6484634,"lon":127.0350361,"dist":775,"kind":"의원","is_gi":false,"drs":1,"addr":"서울특별시 도봉구 도봉로 482, (창동)","tel":"02-903-1818","estb_year":"2006"},{"name":"도담소아청소년과의원","lat":37.6622879,"lon":127.0344681,"dist":787,"kind":"의원","is_gi":false,"drs":1,"addr":"서울특별시 도봉구 방학로 159, (방학동)","tel":"02-955-5357","estb_year":"2005"},{"name":"이영수의원","lat":37.6484381,"lon":127.0342172,"dist":792,"kind":"의원","is_gi":false,"drs":1,"addr":"서울특별시 도봉구 도봉로 477, (쌍문동)","tel":"02-992-6353","estb_year":"1973"},{"name":"동동가정의학과의원","lat":37.6621629,"lon":127.0335988,"dist":794,"kind":"의원","is_gi":false,"drs":2,"addr":"서울특별시 도봉구 방학로 167, 4층 (방학동)","tel":"02-956-0415","estb_year":"2008"},{"name":"유덕기내과의원","lat":37.6620237,"lon":127.0320375,"dist":833,"kind":"의원","is_gi":false,"drs":1,"addr":"서울특별시 도봉구 방학로 183, 3층 (방학동, 거구빌딩)","tel":"02-956-9831","estb_year":"1989"},{"name":"김명진내과의원","lat":37.6478431,"lon":127.0338935,"dist":863,"kind":"의원","is_gi":false,"drs":1,"addr":"서울특별시 도봉구 도봉로 471, (쌍문동)","tel":"02-900-5155","estb_year":"1989"},{"name":"서울탑의원","lat":37.6626358,"lon":127.0327166,"dist":870,"kind":"의원","is_gi":false,"drs":1,"addr":"서울특별시 도봉구 방학로 174, 2층 (방학동)","tel":"02-955-1677","estb_year":"2007"},{"name":"의료법인풍산의료재단 창동제일의원","lat":37.6518962,"lon":127.0454655,"dist":885,"kind":"의원","is_gi":false,"drs":8,"addr":"서울특별시 도봉구 노해로65길 17-13, 2층 (창동, 검진센터)","tel":"02-900-5011","estb_year":"1997"},{"name":"더블유의원","lat":37.6473897,"lon":127.0343912,"dist":902,"kind":"의원","is_gi":false,"drs":5,"addr":"서울특별시 도봉구 도봉로 468, 흥일빌딩 3층 301호 (창동)","tel":"02-990-6868","estb_year":"2015"},{"name":"남상민내과의원","lat":37.6473897,"lon":127.0343912,"dist":902,"kind":"의원","is_gi":false,"drs":1,"addr":"서울특별시 도봉구 도봉로 468, 2층 (창동)","tel":"02-997-9787","estb_year":"2004"},{"name":"상쾌한이비인후과의원","lat":37.6473897,"lon":127.0343912,"dist":902,"kind":"의원","is_gi":false,"drs":1,"addr":"서울특별시 도봉구 도봉로 468, 4층 401호 (창동, 홍일빌딩)","tel":"999-5075","estb_year":"2012"},{"name":"조천영내과의원","lat":37.6530918,"lon":127.0463398,"dist":910,"kind":"의원","is_gi":false,"drs":1,"addr":"서울특별시 도봉구 노해로63길 79, (창동)","tel":"02-994-7582","estb_year":"2002"},{"name":"참벗마취통증의학과의원","lat":37.6530918,"lon":127.0463398,"dist":910,"kind":"의원","is_gi":false,"drs":1,"addr":"서울특별시 도봉구 노해로63길 79, 3층 (창동, 우림빌딩)","tel":"02-998-8275","estb_year":"2014"},{"name":"김민석재활의학과의원","lat":37.6525824,"lon":127.0463482,"dist":928,"kind":"의원","is_gi":false,"drs":1,"addr":"서울특별시 도봉구 노해로63길 78, (창동)","tel":"02-999-4811","estb_year":"1999"},{"name":"더샤인한스의원","lat":37.6514553,"lon":127.0459347,"dist":944,"kind":"의원","is_gi":false,"drs":1,"addr":"서울특별시 도봉구 노해로 341, 101동 307호 (창동, 신원리베르텔)","tel":"990-3002","estb_year":"2012"},{"name":"소화연세소아청소년과의원","lat":37.6514553,"lon":127.0459347,"dist":944,"kind":"의원","is_gi":false,"drs":1,"addr":"서울특별시 도봉구 노해로 341, 신원리베르텔 315호 (창동)","tel":"02-908-6014","estb_year":"2002"},{"name":"마음편한정신건강의학과의원","lat":37.6518117,"lon":127.0462088,"dist":949,"kind":"의원","is_gi":false,"drs":1,"addr":"서울특별시 도봉구 노해로65길 11, 한성빌딩 3층 302호 (창동)","tel":"02-991-9596","estb_year":"1999"},{"name":"이루신내과의원","lat":37.6631104,"lon":127.0411322,"dist":954,"kind":"의원","is_gi":false,"drs":1,"addr":"서울특별시 도봉구 방학로 102, 4층 (방학동)","tel":"02-955-9590","estb_year":"2025"},{"name":"서울이지소아청소년과의원","lat":37.6470525,"lon":127.0333818,"dist":960,"kind":"의원","is_gi":false,"drs":2,"addr":"서울특별시 도봉구 도봉로 461, 3층 (쌍문동, 우림빌딩)","tel":"02-991-5583","estb_year":"2002"},{"name":"더건강내과의원","lat":37.6527457,"lon":127.0470038,"dist":977,"kind":"의원","is_gi":false,"drs":1,"addr":"서울특별시 도봉구 노해로63길 84-3, 5층 (창동)","tel":"02-999-5100","estb_year":"2019"},{"name":"김병철의원","lat":37.6520779,"lon":127.0467721,"dist":983,"kind":"의원","is_gi":false,"drs":1,"addr":"서울특별시 도봉구 노해로65길 14-3, (창동)","tel":"02-974-7852","estb_year":"2014"},{"name":"신동아의원","lat":37.6601767,"lon":127.0270321,"dist":985,"kind":"의원","is_gi":false,"drs":1,"addr":"서울특별시 도봉구 시루봉로 105, 신동아상가 203,204호 (방학동)","tel":"02-954-1857","estb_year":"1988"}]}