{"adm_cd":"11120720","name":"서울특별시 은평구 불광2동","rank":20,"score":0.8031,"center":{"lat":37.62419574699413,"lon":126.9298810672588},"boundary":{"id":"189","type":"Feature","properties":{"adm_nm":"서울특별시 은평구 불광2동","adm_cd2":"1138053000","sgg":"11380","sido":"11","sidonm":"서울특별시","sggnm":"은평구","adm_cd":"11120720"},"geometry":{"type":"Polygon","coordinates":[[[126.94090563582996,37.62570305429628],[126.93965531616568,37.623949606627676],[126.93890285573781,37.62201041025365],[126.93881492278004,37.62098810131676],[126.93832674396533,37.62054525010737],[126.9375357106415,37.62016292056715],[126.93689299226514,37.62002240127371],[126.93477803842416,37.62098573338553],[126.93484680071049,37.62135223083547],[126.93354577245245,37.62172568045144],[126.92641686944611,37.6213318352837],[126.92598409440504,37.62124861050021],[126.92133107240949,37.618869953110874],[126.92050506542829,37.61986659397583],[126.92005852695046,37.620764460256225],[126.91986377254496,37.62158371888348],[126.91974770125107,37.62239435155671],[126.92011208087708,37.62599697841548],[126.91957619848462,37.627963762169166],[126.92558312603595,37.62954345555511],[126.92685138598749,37.62948090984465],[126.92921854116783,37.628382597623094],[126.93212123927522,37.62644144516998],[126.9333326419927,37.6265715932251],[126.94039328287178,37.626032942773115],[126.94090563582996,37.62570305429628]]]}},"station":{"name":"독바위","lat":37.6183371,"lon":126.9330214,"dist_m":706,"n_clinic_500m":1},"metrics":{"c_norm":0.9387,"p_norm":0.8067,"t_norm":0.1771,"pop_total":26159,"pop_40plus":17017,"ratio_40plus":0.6505,"t_raw":39,"t_transit":46,"n_clinic":5,"n_clinic_500m":0,"n_clinic_1km":24,"n_clinic_2km":111,"med_desert":false,"centroid_mismatch":true,"suburban":false},"clinics":[{"name":"이태준김재민내과의원","lat":37.6210849,"lon":126.9251079,"dist":544,"kind":"의원","is_gi":false,"drs":2,"addr":"서울특별시 은평구 연서로 277, 지1,1,2층 (불광동)","tel":"02-359-6397","estb_year":"1993"},{"name":"연신내정형외과의원","lat":37.6203711,"lon":126.9249783,"dist":606,"kind":"의원","is_gi":false,"drs":1,"addr":"서울특별시 은평구 연서로32길 3, (불광동)","tel":"02-357-8872","estb_year":"1997"},{"name":"은평성모이비인후과의원","lat":37.6203711,"lon":126.9249783,"dist":606,"kind":"의원","is_gi":false,"drs":1,"addr":"서울특별시 은평구 연서로32길 3, 정원빌딩 4층 (불광동)","tel":"02-389-0100","estb_year":"2019"},{"name":"연세제일내과의원","lat":37.6203711,"lon":126.9249783,"dist":606,"kind":"의원","is_gi":false,"drs":1,"addr":"서울특별시 은평구 연서로32길 3, 정원빌딩 5층 (불광동)","tel":"02-6010-1140","estb_year":"2020"},{"name":"황이숙내과의원","lat":37.6201712,"lon":126.9232125,"dist":738,"kind":"의원","is_gi":false,"drs":1,"addr":"서울특별시 은평구 연서로 257, (불광동)","tel":"02-352-7929","estb_year":"2000"},{"name":"이선구장원철내과의원","lat":37.6190598,"lon":126.9226206,"dist":857,"kind":"의원","is_gi":false,"drs":2,"addr":"서울특별시 은평구 연서로 246, 6층 (불광동)","tel":"02-389-0120","estb_year":"1991"},{"name":"미즈의원","lat":37.6190598,"lon":126.9226206,"dist":857,"kind":"의원","is_gi":false,"drs":2,"addr":"서울특별시 은평구 연서로 246, 4층 (불광동, 타워크리닉)","tel":"02-358-3535","estb_year":"2005"},{"name":"조은이비인후과의원","lat":37.6190598,"lon":126.9226206,"dist":857,"kind":"의원","is_gi":false,"drs":1,"addr":"서울특별시 은평구 연서로 246, 2층 (불광동)","tel":"02-355-0333","estb_year":"2005"},{"name":"유드림의원","lat":37.6197065,"lon":126.9216803,"dist":878,"kind":"의원","is_gi":false,"drs":1,"addr":"서울특별시 은평구 통일로 856, 10층 10018호 (불광동, 메트로타워)","tel":"02-383-7788","estb_year":"2014"},{"name":"연세메트로마취통증의학과의원","lat":37.6197065,"lon":126.9216803,"dist":878,"kind":"의원","is_gi":false,"drs":5,"addr":"서울특별시 은평구 통일로 856, 2층 (불광동, 메트로타워)","tel":"02-383-8277","estb_year":"2012"},{"name":"박병섭내과의원","lat":37.6234845,"lon":126.9195947,"dist":911,"kind":"의원","is_gi":false,"drs":1,"addr":"서울특별시 은평구 통일로 901, 2층 (갈현동)","tel":"02-389-6600","estb_year":"1991"},{"name":"김성우내과의원","lat":37.6208426,"lon":126.9203999,"dist":915,"kind":"의원","is_gi":false,"drs":1,"addr":"서울특별시 은평구 통일로82길 11, 2층 (불광동)","tel":"02-355-2021","estb_year":"2005"},{"name":"위풍당당재활의학과의원","lat":37.618682,"lon":126.9220944,"dist":920,"kind":"의원","is_gi":false,"drs":3,"addr":"서울특별시 은평구 통일로 842, 1, 2층 (불광동)","tel":"02-386-1100","estb_year":"2022"},{"name":"연신내바른내과의원","lat":37.618682,"lon":126.9220944,"dist":920,"kind":"의원","is_gi":false,"drs":3,"addr":"서울특별시 은평구 통일로 842, 범서빌딩 2층 (불광동)","tel":"02-359-0012","estb_year":"2018"},{"name":"척척마디의원","lat":37.6178285,"lon":126.9227506,"dist":946,"kind":"의원","is_gi":false,"drs":1,"addr":"서울특별시 은평구 통일로 830, 파레제페빌딩 4층 401,402호 (불광동)","tel":"02-389-6944","estb_year":"2018"},{"name":"명인의원","lat":37.6160285,"lon":126.9331306,"dist":950,"kind":"의원","is_gi":false,"drs":1,"addr":"서울특별시 은평구 불광로 104, (불광동)","tel":"02-384-0166","estb_year":"1998"},{"name":"활기찬정형외과의원","lat":37.6211525,"lon":126.9196585,"dist":963,"kind":"의원","is_gi":false,"drs":4,"addr":"서울특별시 은평구 통일로 875, (갈현동, B1층일부,2~5층,6층일부)","tel":"02-385-8875","estb_year":"2007"},{"name":"우리성모안과의원","lat":37.6196002,"lon":126.9204041,"dist":979,"kind":"의원","is_gi":false,"drs":1,"addr":"서울특별시 은평구 통일로 857, 4층 (갈현동, 동우빌딩)","tel":"02-389-7582","estb_year":"2004"},{"name":"(의) 열린의료재단 연신내열린의원","lat":37.619775,"lon":126.9202336,"dist":982,"kind":"의원","is_gi":false,"drs":1,"addr":"서울특별시 은평구 통일로 861, 범일빌딩 6층 (갈현동)","tel":"02-383-7313","estb_year":"2011"},{"name":"유정내과의원","lat":37.6227073,"lon":126.9188906,"dist":983,"kind":"의원","is_gi":false,"drs":1,"addr":"서울특별시 은평구 통일로85길 6-11, (갈현동)","tel":"02-386-9275","estb_year":"1999"},{"name":"서울방사선가정의학과의원","lat":37.6200404,"lon":126.9200222,"dist":984,"kind":"의원","is_gi":false,"drs":1,"addr":"서울특별시 은평구 통일로 863, (갈현동)","tel":"02-355-3505","estb_year":"1990"},{"name":"양전호내과의원","lat":37.6200404,"lon":126.9200222,"dist":984,"kind":"의원","is_gi":false,"drs":1,"addr":"서울특별시 은평구 통일로 863, 2층 (갈현동)","tel":"02-385-2600","estb_year":"2005"},{"name":"지성마취통증의학과의원","lat":37.6200404,"lon":126.9200222,"dist":984,"kind":"의원","is_gi":false,"drs":1,"addr":"서울특별시 은평구 통일로 863, (갈현동)","tel":"02-355-7868","estb_year":"1998"},{"name":"노내과의원","lat":37.618129,"lon":126.921664,"dist":989,"kind":"의원","is_gi":false,"drs":1,"addr":"서울특별시 은평구 통일로 839, (대조동)","tel":"02-389-5050","estb_year":"1994"}]}